{"lobby":{"room":"lobby","teams":{"redrebels":{"name":"Red Rebels","bidders":["t0g3w4n"],"players":["Alec","Kohio","oDeNu","Césarsss","STATS☆Giroh","NIGNO"],"money":1500},"aladosdefinitivos":{"name":"Alados Definitivos","bidders":["pephan","cano"],"players":["Papiloco","SeeD","HuenteFC","(CD) Antoine","Articz"],"money":3000},"lodosos":{"name":"Lodosos","bidders":["chaivon","kurutteheykids"],"players":["Lug","D3*Kalas","G0D OAMS","EK Karuru","PolacoVGC","CHARIN","Dan"],"money":7000},"cinnabar":{"name":"Cinnabar","bidders":["kenneth26"],"players":["KeVGC","SteMaeVGC","EvGT Enri","Maarian","D3-Toasty","Starkro","Conia","El Scorcho","RZ Jordan","Gilberto Ranger"],"money":8500},"laverre":{"name":"Laverre","bidders":["nekronv"],"players":["IsraVGC","Lope","Pancake Raichu"],"money":11000},"patatas":{"name":"Patatas","bidders":["dracko"],"players":["Golden Empoleon","CBreton","HuasoMeta","Mr. Moose","STATS Ike","SebaGomez"],"money":5000},"voltwolves":{"name":"Volt Wolves","bidders":["rav44"],"players":["MAX_LJCR","TDCrackevVGC","Cocano","PuMBeXx"],"money":15500},"simmers":{"name":"Simmers","bidders":["donvgc"],"players":["UCHIHA PKL","AndyVGC","ShineVGC","CDZ","KMV Alexis"],"money":3000},"mistymadness":{"name":"Misty Madness","bidders":["avatarfede"],"players":["Broda","Paracas","Papa de Facu"],"money":15000},"unovadrake":{"name":"Unova Drake","bidders":["haxvic98"],"players":["MolinaVGC","Haxnandez","ChinitoVGC","S.S.Q TITO","Tapu Cokeep"],"money":1500},"spinouts":{"name":"Spin Outs","bidders":["ewokpadawan"],"players":["UB-09","Hunter Walls","SinnohLegenD","IlussiaVGC♤","BEN","Mr. Axe"],"money":6500},"articones":{"name":"ArticOnes","bidders":["juliuspalafox","4rkham"],"players":["LUVIER","Kotbot","VonKoopaCHT!","Ernest Prime"],"money":3000},"stargazingdogs":{"name":"StargazingDogs","bidders":["grow"],"players":["Kodama","LockeVGC","(CD)Haxel","UB-FlyGON","Clifford","SerG*DRAST","Legender"],"money":7500},"tormentas":{"name":"Tormentas","bidders":["suiku"],"players":["Steph","Spiritman!","D3*Darío","TD Reynord","Joaquin Page"],"money":8000},"komalas":{"name":"Komalas","bidders":["alolanmemes"],"players":["FABIAN","RapsodyPK","Samuel :v","ALEX"],"money":11000},"makuhitas":{"name":"Makuhitas","bidders":["rulvgc"],"players":["Aren","EvGT~Colors","Arconte","ek sassan"],"money":3500},"gunners":{"name":"Gunners","bidders":["renevgc"],"players":["Betto","LEO","(CD)Abby"],"money":11000},"dragonsden":{"name":"DragonsDen","bidders":["organometallics"],"players":["AndroidVGC","Boah","Akiva","Danken","Waru"],"money":5500},"elites":{"name":"Elites","bidders":["alanmb27","terrancezer"],"players":["Ruben Linx","CHARLY-616","Geo Stelar","Beto D.","Neroshiny","BozaVGC","Hirams","CD*A.Lee"],"money":3500},"nightmarewarriors":{"name":"Nightmare Warriors","bidders":["pkstfonsi"],"players":["[RZ] Walavii VGC","Darkus","Josh","Haxmani","NimboEC","Cris","Yeiden"],"money":3000}},"players":{"nano":{"name":"Nano","Nick name":"Nano","ORAS":"x","BW":"x","DPP":"x","ADV":"x","XY\r":"x\r"},"matt":{"name":"Matt","Nick name":"Matt","ORAS":"x","BW":"x","DPP":"x","ADV":"x","XY\r":"x\r"},"kanchi":{"name":"Kanchi","Nick name":"Kanchi","ORAS":"x","BW":"x","DPP":"x","ADV":"x","XY\r":"x\r"},"kesuke":{"name":"Kesuke","Nick name":"Kesuke","ORAS":"x","BW":"x","DPP":"x","ADV":"x","XY\r":"x\r"},"jmacboy":{"name":"jmacboy","Nick name":"jmacboy","ORAS":"x","BW":"x","DPP":"x","ADV":"x","XY\r":"x\r"},"marthyx":{"name":"Marthyx","Nick name":"Marthyx","ORAS":"x","BW":"x","DPP":"x","ADV":"x","XY\r":"x\r"},"walves":{"name":"Walves","Nick name":"Walves","ORAS":"x","BW":"x","DPP":"x","ADV":"x","XY\r":"x\r"},"juninho":{"name":"Juninho","Nick name":"Juninho","ORAS":"x","BW":"x","DPP":"x","ADV":"x","XY\r":"x\r"},"darkomega2001":{"name":"DarkOmega2001","Nick name":"DarkOmega2001","ORAS":"x","BW":"x","DPP":"x","ADV":"x","XY\r":"x\r"},"sitrusvgc":{"name":"SitrusVGC","Nick name":"SitrusVGC","ORAS":"x","BW":"x","DPP":"x","ADV":"x","XY\r":"x\r"},"makiseptv":{"name":"Makise PTV","Nick name":"Makise PTV","ORAS":"x","BW":"x","DPP":"x","ADV":"x","XY\r":"x\r"},"s3rg1otg":{"name":"S3RG1O TG","Nick name":"S3RG1O TG","ORAS":"x","BW":"x","DPP":"x","ADV":"x","XY\r":"x\r"},"sensualitotg":{"name":"SensuaLitoTG","Nick name":"SensuaLitoTG","ORAS":"x","BW":"x","DPP":"x","ADV":"x","XY\r":"x\r"},"kamaldaniel":{"name":"Kamal Daniel","Nick name":"Kamal Daniel","ORAS":"x","BW":"x","DPP":"x","ADV":"x","XY\r":"x\r"},"thefangptv":{"name":"The Fang PTV","Nick name":"The Fang PTV","ORAS":"x","BW":"x","DPP":"x","ADV":"x","XY\r":"x\r"},"arian":{"name":"ARIAN","Nick name":"ARIAN","ORAS":"x","BW":"x","DPP":"x","ADV":"x","XY\r":"x\r"},"stever":{"name":"STEVER","Nick name":"STEVER","ORAS":"x","BW":"x","DPP":"x","ADV":"x","XY\r":"x\r"},"seto":{"name":"Seto","Nick name":"Seto","ORAS":"x","BW":"x","DPP":"x","ADV":"x","XY\r":"x\r"},"hapk":{"name":"HaPK","Nick name":"HaPK","ORAS":"x","BW":"x","DPP":"x","ADV":"x","XY\r":"x\r"},"laulau":{"name":"Lau-Lau","Nick name":"Lau-Lau","ORAS":"x","BW":"x","DPP":"x","ADV":"x","XY\r":"x\r"},"rukairo":{"name":"Rukairo","Nick name":"Rukairo ","ORAS":"x","BW":"x","DPP":"x","ADV":"x","XY\r":"x\r"},"sawyer":{"name":"sawyer","Nick name":"sawyer","ORAS":"x","BW":"x","DPP":"x","ADV":"x","XY\r":"x\r"},"chino":{"name":"Chino","Nick name":"Chino","ORAS":"x","BW":"x","DPP":"x","ADV":"x","XY\r":"x\r"},"prepo":{"name":"Prepo","Nick name":"Prepo","ORAS":"x","BW":"x","DPP":"x","ADV":"x","XY\r":"x\r"},"joan":{"name":"Joan","Nick name":"Joan","ORAS":"x","BW":"x","DPP":"x","ADV":"x","XY\r":"x\r"},"fbernard":{"name":"FBernard","Nick name":"FBernard","ORAS":"x","BW":"x","DPP":"x","ADV":"x","XY\r":"x\r"},"ssqvega":{"name":"SSQ~Vega","Nick name":"SSQ~Vega","ORAS":"x","BW":"x","DPP":"x","ADV":"x","XY\r":"x\r"},"tosty":{"name":"Tosty","Nick name":"Tosty","ORAS":"x","BW":"x","DPP":"x","ADV":"x","XY\r":"x\r"},"ranza":{"name":"Ranza","Nick name":"Ranza","ORAS":"x","BW":"x","DPP":"x","ADV":"x","XY\r":"x\r"},"masis":{"name":"Masis","Nick name":"Masis","ORAS":"x","BW":"x","DPP":"x","ADV":"x","XY\r":"x\r"},"chavesvgc":{"name":"ChavesVGC","Nick name":"ChavesVGC ","ORAS":"x","BW":"x","DPP":"x","ADV":"x","XY\r":"x\r"},"santa":{"name":"Santa","Nick name":"Santa","ORAS":"x","BW":"x","DPP":"x","ADV":"x","XY\r":"x\r"},"fuentes":{"name":"Fuentes","Nick name":"Fuentes","ORAS":"x","BW":"x","DPP":"x","ADV":"x","XY\r":"x\r"},"marger":{"name":"MARGER","Nick name":"MARGER","ORAS":"x","BW":"x","DPP":"x","ADV":"x","XY\r":"x\r"},"guillo":{"name":"Guillo","Nick name":"Guillo","ORAS":"x","BW":"x","DPP":"x","ADV":"x","XY\r":"x\r"},"d3kelvin":{"name":"D3*Kelvin","Nick name":"D3*Kelvin","ORAS":"x","BW":"x","DPP":"x","ADV":"x","XY\r":"x\r"},"josamus":{"name":"Josamus","Nick name":"Josamus","ORAS":"x","BW":"x","DPP":"x","ADV":"x","XY\r":"x\r"},"aobachan":{"name":"Aoba-chan","Nick name":"Aoba-chan","ORAS":"x","BW":"x","DPP":"x","ADV":"x","XY\r":"x\r"},"evgtdadoo":{"name":"EvGT~Dadoo","Nick name":"EvGT~Dadoo","ORAS":"x","BW":"x","DPP":"x","ADV":"x","XY\r":"x\r"},"ian":{"name":"IAN","Nick name":"IAN","ORAS":"x","BW":"x","DPP":"x","ADV":"x","XY\r":"x\r"},"bastianvgc":{"name":"Bastian VGC","Nick name":"Bastian VGC","ORAS":"x","BW":"x","DPP":"x","ADV":"x","XY\r":"x\r"},"julius":{"name":"Julius","Nick name":"Julius","ORAS":"x","BW":"x","DPP":"x","ADV":"x","XY\r":"x\r"},"evgtpol":{"name":"EvGT~POL","Nick name":"EvGT~POL","ORAS":"x","BW":"x","DPP":"x","ADV":"x","XY\r":"x\r"},"slayer":{"name":"Slayer","Nick name":"Slayer","ORAS":"x","BW":"x","DPP":"x","ADV":"x","XY\r":"x\r"},"dandrast":{"name":"Dan*DRAST","Nick name":"Dan*DRAST","ORAS":"x","BW":"x","DPP":"x","ADV":"x","XY\r":"x\r"},"wolf":{"name":"wolf","Nick name":"wolf","ORAS":"x","BW":"x","DPP":"x","ADV":"x","XY\r":"x\r"},"miza":{"name":"MIZA","Nick name":"MIZA","ORAS":"x","BW":"x","DPP":"x","ADV":"x","XY\r":"x\r"},"chonk":{"name":"Chonk","Nick name":"Chonk","ORAS":"x","BW":"x","DPP":"x","ADV":"x","XY\r":"x\r"},"asrielvgc":{"name":"Asriel VGC","Nick name":"Asriel VGC","ORAS":"x","BW":"x","DPP":"x","ADV":"x","XY\r":"x\r"},"jhos75":{"name":"Jhos75","Nick name":"Jhos75","ORAS":"x","BW":"x","DPP":"x","ADV":"x","XY\r":"x\r"},"pokcarlos24":{"name":"POKCARLOS24","Nick name":"POKCARLOS24","ORAS":"x","BW":"x","DPP":"x","ADV":"x","XY\r":"x\r"},"dagegoroid":{"name":"Dagegoroid","Nick name":"Dagegoroid","ORAS":"x","BW":"x","DPP":"x","ADV":"x","XY\r":"x\r"},"inxmaneater":{"name":"INX-Maneater","Nick name":"INX-Maneater","ORAS":"x","BW":"x","DPP":"x","ADV":"x","XY\r":"x\r"},"davidbravebird":{"name":"David Brave bird","Nick name":"David Brave bird","ORAS":"x","BW":"x","DPP":"x","ADV":"x","XY\r":"x\r"},"rainy":{"name":"Rainy","Nick name":"Rainy","ORAS":"x","BW":"x","DPP":"x","ADV":"x","XY\r":"x\r"},"kaoz":{"name":"Kaoz","Nick name":"Kaoz","ORAS":"x","BW":"x","DPP":"x","ADV":"x","XY\r":"x\r"},"andy":{"name":"Andy","Nick name":"Andy","ORAS":"x","BW":"x","DPP":"x","ADV":"x","XY\r":"x\r"},"celoriorp":{"name":"CelorioRP","Nick name":"CelorioRP","ORAS":"x","BW":"x","DPP":"x","ADV":"x","XY\r":"x\r"},"alan":{"name":"Alan","Nick name":"Alan","ORAS":"x","BW":"x","DPP":"x","ADV":"x","XY\r":"x\r"},"mostro":{"name":"Mostro","Nick name":"Mostro","ORAS":"x","BW":"x","DPP":"x","ADV":"x","XY\r":"x\r"},"francisco":{"name":"Francisco","Nick name":"Francisco","ORAS":"x","BW":"x","DPP":"x","ADV":"x","XY\r":"x\r"},"kotori":{"name":"Kotori ~","Nick name":"Kotori ~","ORAS":"x","BW":"x","DPP":"x","ADV":"x","XY\r":"x\r"},"iveel":{"name":"IveeL","Nick name":"IveeL","ORAS":"x","BW":"x","DPP":"x","ADV":"x","XY\r":"x\r"},"koreano":{"name":"Koreano","Nick name":"Koreano","ORAS":"x","BW":"x","DPP":"x","ADV":"x","XY\r":"x\r"},"alisha":{"name":"★Alisha★","Nick name":"★Alisha★","ORAS":"x","BW":"x","DPP":"x","ADV":"x","XY\r":"x\r"},"mike":{"name":"Mike","Nick name":"Mike","ORAS":"x","BW":"x","DPP":"x","ADV":"x","XY\r":"x\r"},"tonx":{"name":"Tonx","Nick name":"Tonx","ORAS":"x","BW":"x","DPP":"x","ADV":"x","XY\r":"x\r"},"kamuigp":{"name":"KamuiGP","Nick name":"KamuiGP","ORAS":"x","BW":"x","DPP":"x","ADV":"x","XY\r":"x\r"},"dogeswag":{"name":"DogeSwag","Nick name":"DogeSwag","ORAS":"x","BW":"x","DPP":"x","ADV":"x","XY\r":"x\r"},"aizenmack":{"name":"Aizenmack","Nick name":"Aizenmack","ORAS":"x","BW":"x","DPP":"x","ADV":"x","XY\r":"x\r"},"gazpacho":{"name":"Gazpacho","Nick name":"Gazpacho","ORAS":"x","BW":"x","DPP":"x","ADV":"x","XY\r":"x\r"},"nicole":{"name":"*nicole*","Nick name":"*nicole*","ORAS":"x","BW":"x","DPP":"x","ADV":"x","XY\r":"x\r"},"knez200":{"name":"Knez200","Nick name":"Knez200","ORAS":"x","BW":"x","DPP":"x","ADV":"x","XY\r":"x\r"},"karlox":{"name":"Karlox","Nick name":"Karlox","ORAS":"x","BW":"x","DPP":"x","ADV":"x","XY\r":"x\r"},"luisg":{"name":"Luis G","Nick name":"Luis G","ORAS":"x","BW":"x","DPP":"x","ADV":"x","XY\r":"x\r"},"altair":{"name":"Altair","Nick name":"Altair","ORAS":"x","BW":"x","DPP":"x","ADV":"x","XY\r":"x\r"},"hecotoro":{"name":"Hecotoro","Nick name":"Hecotoro","ORAS":"x","BW":"x","DPP":"x","ADV":"x","XY\r":"x\r"},"danteid":{"name":"Dante*I.D*","Nick name":"Dante*I.D*","ORAS":"x","BW":"x","DPP":"x","ADV":"x","XY\r":"x\r"},"istroveca":{"name":"IstroVeca","Nick name":"IstroVeca","ORAS":"x","BW":"x","DPP":"x","ADV":"x","XY\r":"x\r"},"mrcubine243":{"name":"Mrcubine243","Nick name":"Mrcubine243","ORAS":"x","BW":"x","DPP":"x","ADV":"x","XY\r":"x\r"},"iza":{"name":"Iza","Nick name":"Iza","ORAS":"x","BW":"x","DPP":"x","ADV":"x","XY\r":"x\r"},"makenda":{"name":"Makenda","Nick name":"Makenda","ORAS":"x","BW":"x","DPP":"x","ADV":"x","XY\r":"x\r"},"haxgeminicam":{"name":"HaxGeminiCAM","Nick name":"HaxGeminiCAM","ORAS":"x","BW":"x","DPP":"x","ADV":"x","XY\r":"x\r"},"srmomo":{"name":"SrMomo","Nick name":"SrMomo","ORAS":"x","BW":"x","DPP":"x","ADV":"x","XY\r":"x\r"},"zhino":{"name":"Zhino","Nick name":"Zhino","ORAS":"x","BW":"x","DPP":"x","ADV":"x","XY\r":"x\r"},"edgar":{"name":"Edgar","Nick name":"Edgar","ORAS":"x","BW":"x","DPP":"x","ADV":"x","XY\r":"x\r"},"chimalltlin":{"name":"Chimalltlin","Nick name":"Chimalltlin","ORAS":"x","BW":"x","DPP":"x","ADV":"x","XY\r":"x\r"},"chemavgc":{"name":"Chema VGC","Nick name":"Chema VGC","ORAS":"x","BW":"x","DPP":"x","ADV":"x","XY\r":"x\r"},"missingno02andre":{"name":"Missing_no02/Andreé","Nick name":"Missing_no02/Andreé","ORAS":"x","BW":"x","DPP":"x","ADV":"x","XY\r":"x\r"},"enser":{"name":"En ser","Nick name":"En ser ","ORAS":"x","BW":"x","DPP":"x","ADV":"x","XY\r":"x\r"},"adri":{"name":"Adri","Nick name":"Adri","ORAS":"x","BW":"x","DPP":"x","ADV":"x","XY\r":"x\r"},"ivan":{"name":"Ivan","Nick name":"Ivan","ORAS":"x","BW":"x","DPP":"x","ADV":"x","XY\r":"x\r"},"yico":{"name":"Yico","Nick name":"Yico","ORAS":"x","BW":"x","DPP":"x","ADV":"x","XY\r":"x\r"},"osvaldo":{"name":"Osvaldo","Nick name":"Osvaldo","ORAS":"x","BW":"x","DPP":"x","ADV":"x","XY\r":"x\r"},"asimov":{"name":"Asimov","Nick name":"Asimov","ORAS":"x","BW":"x","DPP":"x","ADV":"x","XY\r":"x\r"},"inxdan":{"name":"INX*Dan","Nick name":"INX*Dan","ORAS":"x","BW":"x","DPP":"x","ADV":"x","XY\r":"x\r"},"carlos":{"name":"CarLos","Nick name":"CarLos","ORAS":"x","BW":"x","DPP":"x","ADV":"x","XY\r":"x\r"},"rangerhax":{"name":"Ranger Hax","Nick name":"Ranger Hax","ORAS":"x","BW":"x","DPP":"x","ADV":"x","XY\r":"x\r"},"rapbito":{"name":"Rapbito","Nick name":"Rapbito","ORAS":"x","BW":"x","DPP":"x","ADV":"x","XY\r":"x\r"},"shyleafeon":{"name":"ShyLeafeon","Nick name":"ShyLeafeon","ORAS":"x","BW":"x","DPP":"x","ADV":"x","XY\r":"x\r"},"omegazero":{"name":"OmegaZero","Nick name":"OmegaZero","ORAS":"x","BW":"x","DPP":"x","ADV":"x","XY\r":"x\r"},"cpserchs":{"name":"CP SERCH'S","Nick name":"CP SERCH'S","ORAS":"x","BW":"x","DPP":"x","ADV":"x","XY\r":"x\r"},"enloz":{"name":"\"Enloz","Nick name":"\"Enloz","ORAS":" Elder Lugia o Héctor\"","BW":"x","DPP":"x","ADV":"x","XY\r":"x"},"daniel":{"name":"Daniel","Nick name":"Daniel","ORAS":"x","BW":"x","DPP":"x","ADV":"x","XY\r":"x\r"},"milgram":{"name":"Milgram","Nick name":"Milgram","ORAS":"x","BW":"x","DPP":"x","ADV":"x","XY\r":"x\r"},"omar":{"name":"Omar","Nick name":"Omar","ORAS":"x","BW":"x","DPP":"x","ADV":"x","XY\r":"x\r"},"ocean":{"name":"Ocean","Nick name":"Ocean","ORAS":"x","BW":"x","DPP":"x","ADV":"x","XY\r":"x\r"},"vicius":{"name":"Vicius","Nick name":"Vicius","ORAS":"x","BW":"x","DPP":"x","ADV":"x","XY\r":"x\r"},"rems":{"name":"Rems","Nick name":"Rems","ORAS":"x","BW":"x","DPP":"x","ADV":"x","XY\r":"x\r"},"westlo":{"name":"Westlo","Nick name":"Westlo","ORAS":"x","BW":"x","DPP":"x","ADV":"x","XY\r":"x\r"},"arkanis":{"name":"Arkanis","Nick name":"Arkanis","ORAS":"x","BW":"x","DPP":"x","ADV":"x","XY\r":"x\r"},"kyoya":{"name":"Kyoya","Nick name":"Kyoya","ORAS":"x","BW":"x","DPP":"x","ADV":"x","XY\r":"x\r"},"gupi":{"name":"Gupi","Nick name":"Gupi","ORAS":"x","BW":"x","DPP":"x","ADV":"x","XY\r":"x\r"},"borrego":{"name":"Borrego","Nick name":"Borrego","ORAS":"x","BW":"x","DPP":"x","ADV":"x","XY\r":"x\r"},"moiss":{"name":"Moisés","Nick name":"Moisés","ORAS":"x","BW":"x","DPP":"x","ADV":"x","XY\r":"x\r"},"pknaviangie":{"name":"PkNavi*Angie","Nick name":"PkNavi*Angie","ORAS":"x","BW":"x","DPP":"x","ADV":"x","XY\r":"x\r"},"addi":{"name":"Addi","Nick name":"Addi","ORAS":"x","BW":"x","DPP":"x","ADV":"x","XY\r":"x\r"},"robbfucu":{"name":"rObbfucu","Nick name":"rObbfucu","ORAS":"x","BW":"x","DPP":"x","ADV":"x","XY\r":"x\r"},"gonsser":{"name":"Gonsser","Nick name":"Gonsser","ORAS":"x","BW":"x","DPP":"x","ADV":"x","XY\r":"x\r"},"darkap7":{"name":"Darkap7","Nick name":"Darkap7","ORAS":"x","BW":"x","DPP":"x","ADV":"x","XY\r":"x\r"},"aj":{"name":"AJ","Nick name":"AJ","ORAS":"x","BW":"x","DPP":"x","ADV":"x","XY\r":"x\r"},"yami":{"name":"Yami","Nick name":"Yami","ORAS":"x","BW":"x","DPP":"x","ADV":"x","XY\r":"x\r"},"deztruktor":{"name":"Deztruktor","Nick name":"Deztruktor","ORAS":"x","BW":"x","DPP":"x","ADV":"x","XY\r":"x\r"},"raul":{"name":"RauL","Nick name":"RauL ","ORAS":"x","BW":"x","DPP":"x","ADV":"x","XY\r":"x\r"},"maggot":{"name":"Maggot","Nick name":"Maggot","ORAS":"x","BW":"x","DPP":"x","ADV":"x","XY\r":"x\r"},"mobiusdrast":{"name":"Mobius☆DRAST","Nick name":"Mobius☆DRAST ","ORAS":"x","BW":"x","DPP":"x","ADV":"x","XY\r":"x\r"},"devilqwertycharles":{"name":"DevilQWERTY/Charles","Nick name":"DevilQWERTY/Charles","ORAS":"x","BW":"x","DPP":"x","ADV":"x","XY\r":"x\r"},"nidael1":{"name":"Nidael1","Nick name":"Nidael1","ORAS":"x","BW":"x","DPP":"x","ADV":"x","XY\r":"x\r"},"inxcharlie":{"name":"Inx Charlie","Nick name":"Inx Charlie","ORAS":"x","BW":"x","DPP":"x","ADV":"x","XY\r":"x\r"},"luis":{"name":"Luis","Nick name":"Luis","ORAS":"x","BW":"x","DPP":"x","ADV":"x","XY\r":"x\r"},"inxpain":{"name":"INX Pain","Nick name":"INX Pain","ORAS":"x","BW":"x","DPP":"x","ADV":"x","XY\r":"x\r"},"golondrina":{"name":"Golondrina","Nick name":"Golondrina ","ORAS":"x","BW":"x","DPP":"x","ADV":"x","XY\r":"x\r"},"jhon":{"name":"Jhon","Nick name":"Jhon ","ORAS":"x","BW":"x","DPP":"x","ADV":"x","XY\r":"x\r"},"sentry":{"name":"Sentry","Nick name":"Sentry ","ORAS":"x","BW":"x","DPP":"x","ADV":"x","XY\r":"x\r"},"blackner":{"name":"Blackner","Nick name":"Blackner","ORAS":"x","BW":"x","DPP":"x","ADV":"x","XY\r":"x\r"},"coraje":{"name":"Coraje","Nick name":"Coraje","ORAS":"x","BW":"x","DPP":"x","ADV":"x","XY\r":"x\r"},"ajax":{"name":"Ajax","Nick name":"Ajax ","ORAS":"x","BW":"x","DPP":"x","ADV":"x","XY\r":"x\r"},"emil":{"name":"EmiL","Nick name":"EmiL","ORAS":"x","BW":"x","DPP":"x","ADV":"x","XY\r":"x\r"},"ethan":{"name":"Ethan","Nick name":"Ethan","ORAS":"x","BW":"x","DPP":"x","ADV":"x","XY\r":"x\r"},"terrance":{"name":"Terrance","Nick name":"Terrance","ORAS":"x","BW":"x","DPP":"x","ADV":"x","XY\r":"x\r"},"trampas":{"name":"\"Trampas","Nick name":"\"Trampas","ORAS":" in game Arlenne. \"","BW":"x","DPP":"x","ADV":"x","XY\r":"x"},"alexander":{"name":"Alexander","Nick name":"Alexander ","ORAS":"x","BW":"x","DPP":"x","ADV":"x","XY\r":"x\r"},"hamudivgc":{"name":"HamudiVGC","Nick name":"HamudiVGC","ORAS":"x","BW":"x","DPP":"x","ADV":"x","XY\r":"x\r"},"nilzeus":{"name":"Nilzeus","Nick name":"Nilzeus","ORAS":"x","BW":"x","DPP":"x","ADV":"x","XY\r":"x\r"},"satoshijys":{"name":"Satoshi-JyS*","Nick name":"Satoshi-JyS*","ORAS":"x","BW":"x","DPP":"x","ADV":"x","XY\r":"x\r"},"cala":{"name":"Cala","Nick name":"Cala","ORAS":"x","BW":"x","DPP":"x","ADV":"x","XY\r":"x\r"},"mrcoquis":{"name":"MrCoquis•","Nick name":"MrCoquis•","ORAS":"x","BW":"x","DPP":"x","ADV":"x","XY\r":"x\r"},"charass":{"name":"CharaSS","Nick name":"CharaSS","ORAS":"x","BW":"x","DPP":"x","ADV":"x","XY\r":"x\r"},"zber":{"name":"Záber","Nick name":"Záber","ORAS":"x","BW":"x","DPP":"x","ADV":"x","XY\r":"x\r"},"regizz":{"name":"Regizz","Nick name":"Regizz","ORAS":"x","BW":"x","DPP":"x","ADV":"x","XY\r":"x\r"},"goldd":{"name":"Goldd","Nick name":"Goldd","ORAS":"x","BW":"x","DPP":"x","ADV":"x","XY\r":"x\r"},"mrdrew":{"name":"Mr Drew","Nick name":"Mr Drew","ORAS":"x","BW":"x","DPP":"x","ADV":"x","XY\r":"x\r"},"diegodm26":{"name":"DiegoDM26","Nick name":"DiegoDM26","ORAS":"x","BW":"x","DPP":"x","ADV":"x","XY\r":"x"}},"state":"start","managers":{"t0g3w4n":"redrebels","pephan":"aladosdefinitivos","chaivon":"lodosos","kenneth26":"cinnabar","nekronv":"laverre","dracko":"patatas","rav44":"voltwolves","donvgc":"simmers","avatarfede":"mistymadness","haxvic98":"unovadrake","ewokpadawan":"spinouts","juliuspalafox":"articones","grow":"stargazingdogs","suiku":"tormentas","alolanmemes":"komalas","rulvgc":"makuhitas","renevgc":"gunners","organometallics":"dragonsden","alanmb27":"elites","pkstfonsi":"nightmarewarriors","terrancezer":"elites","kurutteheykids":"lodosos","cano":"aladosdefinitivos","4rkham":"articones"},"activeTeams":["aladosdefinitivos","lodosos","cinnabar","patatas","voltwolves","mistymadness","spinouts","articones","stargazingdogs","tormentas","komalas","makuhitas","dragonsden","elites"],"nomination":"aladosdefinitivos","currDirr":-1,"nominee":null,"bid":null,"topBidder":"cano","timer":{"_called":true,"_idleTimeout":5000,"_idlePrev":null,"_idleNext":null,"_idleStart":14074776,"_repeat":null},"draftlog":[["purchase","Golden Empoleon",24500,"Patatas"],["purchase","MAX_LJCR",50000,"Volt Wolves"],["purchase","MolinaVGC",41000,"Unova Drake"],["purchase","Ruben Linx",22500,"Elites"],["purchase","AndroidVGC",40000,"DragonsDen"],["purchase","LUVIER",39000,"ArticOnes"],["purchase","TDCrackevVGC",29000,"Volt Wolves"],["purchase","UCHIHA PKL",3000,"Simmers"],["purchase","Boah",50000,"DragonsDen"],["purchase","Haxnandez",51000,"Unova Drake"],["purchase","Papiloco",52000,"Alados Definitivos"],["purchase","Broda",30000,"Misty Madness"],["purchase","Lug",19000,"Lodosos"],["purchase","[RZ] Walavii VGC",37000,"Nightmare Warriors"],["purchase","CHARLY-616",24000,"Elites"],["purchase","D3*Kalas",25500,"Lodosos"],["purchase","AndyVGC",50000,"Simmers"],["purchase","Alec",12000,"Red Rebels"],["purchase","Cranidactyl",19500,"Cinnabar"],["removal","Cranidactyl","Cinnabar"],["purchase","Darkus",9000,"Nightmare Warriors"],["purchase","Josh",10000,"Nightmare Warriors"],["purchase","Geo Stelar",21000,"Elites"],["purchase","Akiva",10000,"DragonsDen"],["purchase","UB-09",42500,"Spin Outs"],["purchase","Paracas",15000,"Misty Madness"],["purchase","Cocano",17000,"Volt Wolves"],["purchase","CBreton",11000,"Patatas"],["purchase","G0D OAMS",13000,"Lodosos"],["purchase","IsraVGC",35500,"Laverre"],["purchase","Papa de Facu",60000,"Misty Madness"],["purchase","ChinitoVGC",3000,"Unova Drake"],["purchase","Kotbot",20000,"ArticOnes"],["purchase","ShineVGC",3000,"Simmers"],["purchase","PuMBeXx",8500,"Volt Wolves"],["purchase","Aren",42500,"Makuhitas"],["purchase","Lope",23500,"Laverre"],["purchase","Betto",22000,"Gunners"],["purchase","EK Karuru",3000,"Lodosos"],["purchase","SeeD",17000,"Alados Definitivos"],["purchase","Kohio",7000,"Red Rebels"],["purchase","oDeNu",6500,"Red Rebels"],["purchase","EvGT~Colors",18000,"Makuhitas"],["purchase","PolacoVGC",11500,"Lodosos"],["purchase","VonKoopaCHT!",6000,"ArticOnes"],["purchase","Pancake Raichu",20000,"Laverre"],["purchase","Kodama",35500,"StargazingDogs"],["purchase","S.S.Q TITO",14000,"Unova Drake"],["purchase","FABIAN",31500,"Komalas"],["purchase","Hunter Walls",28500,"Spin Outs"],["purchase","LEO",13000,"Gunners"],["purchase","KeVGC",10000,"Cinnabar"],["purchase","Haxmani",5000,"Nightmare Warriors"],["purchase","LockeVGC",5500,"StargazingDogs"],["purchase","(CD)Haxel",14500,"StargazingDogs"],["purchase","Arconte",7500,"Makuhitas"],["purchase","SteMaeVGC",6500,"Cinnabar"],["purchase","EvGT Enri",20000,"Cinnabar"],["purchase","Danken",6500,"DragonsDen"],["purchase","Beto D.",12000,"Elites"],["purchase","RapsodyPK",27000,"Komalas"],["purchase","NimboEC",3000,"Nightmare Warriors"],["purchase","(CD)Abby",44000,"Gunners"],["purchase","Waru",8000,"DragonsDen"],["purchase","Césarsss",28000,"Red Rebels"],["purchase","ek sassan",18500,"Makuhitas"],["purchase","Neroshiny",22000,"Elites"],["purchase","Steph",16000,"Tormentas"],["purchase","UB-FlyGON",26500,"StargazingDogs"],["purchase","Spiritman!",16000,"Tormentas"],["purchase","CDZ",21000,"Simmers"],["purchase","Maarian",19000,"Cinnabar"],["purchase","Cris",20000,"Nightmare Warriors"],["purchase","SinnohLegenD",20000,"Spin Outs"],["purchase","D3*Darío",20000,"Tormentas"],["purchase","D3-Toasty",7000,"Cinnabar"],["purchase","IlussiaVGC♤",10500,"Spin Outs"],["purchase","CHARIN",5500,"Lodosos"],["purchase","HuenteFC",9000,"Alados Definitivos"],["purchase","STATS☆Giroh",19500,"Red Rebels"],["purchase","NIGNO",15500,"Red Rebels"],["purchase","Clifford",12500,"StargazingDogs"],["purchase","Dan",5500,"Lodosos"],["purchase","Samuel :v",42000,"Komalas"],["purchase","KMV Alexis",10000,"Simmers"],["purchase","HuasoMeta",14000,"Patatas"],["purchase","TD Reynord",23000,"Tormentas"],["purchase","ALEX",8500,"Komalas"],["purchase","Starkro",11000,"Cinnabar"],["purchase","BEN",9000,"Spin Outs"],["purchase","Joaquin Page",37000,"Tormentas"],["purchase","Mr. Moose",16000,"Patatas"],["purchase","SerG*DRAST",14000,"StargazingDogs"],["purchase","Conia",8000,"Cinnabar"],["purchase","MilosRaul",3000,"Makuhitas"],["purchase","(CD) Antoine",6000,"Alados Definitivos"],["purchase","BozaVGC",6000,"Elites"],["purchase","Yeiden",3000,"Nightmare Warriors"],["purchase","Hirams",3000,"Elites"],["purchase","CD*A.Lee",8500,"Elites"],["purchase","Tapu Cokeep",9500,"Unova Drake"],["purchase","El Scorcho",6000,"Cinnabar"],["purchase","Legender",4000,"StargazingDogs"],["purchase","Ernest Prime",22000,"ArticOnes"],["purchase","Mr. Axe",3000,"Spin Outs"],["purchase","RZ Jordan",18000,"Cinnabar"],["purchase","STATS Ike",4500,"Patatas"],["removal","MilosRaul","Makuhitas"],["purchase","SebaGomez",15000,"Patatas"],["purchase","Gilberto Ranger",6000,"Cinnabar"],["purchase","Articz",3000,"Alados Definitivos"]]}}